message_db/__init__.py
message_db/client.py
message_db/connection.py
message_db_py-0.2.0.dist-info/LICENSE
message_db_py-0.2.0.dist-info/METADATA
message_db_py-0.2.0.dist-info/WHEEL
message_db_py-0.2.0.dist-info/RECORD
