Metadata-Version: 2.1
Name: message-db-py
Version: 0.2.0
Summary: The Python interface to the MessageDB Event Store and Message Store
License: MIT
Keywords: message-db,event-sourcing,event-store,messaging,cqrs,command-query-responsibility-segregation,events,streaming,database,postgresql,python,async,microservices,distributed-systems,message-queue,event-driven,real-time
Author: Subhash Bhushan
Author-email: subhash.bhushan@gmail.com
Requires-Python: >=3.9,<4.0
Classifier: Development Status :: 4 - Beta
Classifier: Intended Audience :: Developers
Classifier: Intended Audience :: Information Technology
Classifier: License :: OSI Approved :: MIT License
Classifier: Operating System :: OS Independent
Classifier: Programming Language :: Python
Classifier: Programming Language :: Python :: 3
Classifier: Programming Language :: Python :: 3.9
Classifier: Programming Language :: Python :: 3.10
Classifier: Programming Language :: Python :: 3.11
Classifier: Programming Language :: Python :: 3.12
Classifier: Topic :: Database
Classifier: Topic :: Database :: Database Engines/Servers
Classifier: Topic :: Software Development :: Libraries
Classifier: Topic :: Software Development :: Libraries :: Python Modules
Requires-Dist: psycopg2 (>=2.9.9,<3.0.0)
